grim_reaper/__init__.py
grim_reaper/post_install.py
grim_reaper-1.0.36.dist-info/METADATA
grim_reaper-1.0.36.dist-info/WHEEL
grim_reaper-1.0.36.dist-info/entry_points.txt
grim_reaper-1.0.36.dist-info/top_level.txt
grim_reaper-1.0.36.dist-info/RECORD
