Metadata-Version: 2.1
Name: grim-reaper
Version: 1.0.36
Summary: Death Defying Data Protection - When data death comes knocking, Grim ensures resurrection is just a command away
Home-page: https://grim.so
Author: Bernie Gengel and his beagle Buddy
Author-email: Bernie Gengel and his beagle Buddy <rip@grim.so>
Project-URL: Homepage, https://grim.so
Project-URL: Documentation, https://grim.so/docs
Project-URL: Repository, https://github.com/cyber-boost/grim
Project-URL: Bug Tracker, https://github.com/cyber-boost/grim/issues
Keywords: backup,monitoring,security,grim,encryption,compression,deduplication,license-protection
Platform: any
Classifier: Development Status :: 5 - Production/Stable
Classifier: Environment :: Console
Classifier: Intended Audience :: Developers
Classifier: Intended Audience :: System Administrators
Classifier: Operating System :: OS Independent
Classifier: Programming Language :: Python :: 3
Classifier: Programming Language :: Python :: 3.8
Classifier: Programming Language :: Python :: 3.9
Classifier: Programming Language :: Python :: 3.10
Classifier: Programming Language :: Python :: 3.11
Classifier: Programming Language :: Python :: 3.12
Classifier: Topic :: System :: Archiving :: Backup
Classifier: Topic :: System :: Systems Administration
Classifier: Topic :: Security
Requires-Python: >=3.8
Requires-Dist: aiohttp >=3.8.0
Requires-Dist: click >=8.0.0
Requires-Dist: pathlib >=1.0.0
Requires-Dist: psutil >=5.8.0
Requires-Dist: pyyaml >=6.0
Requires-Dist: requests >=2.25.0
Requires-Dist: typing-extensions >=4.0.0
Provides-Extra: dev
Requires-Dist: black >=21.0 ; extra == 'dev'
Requires-Dist: flake8 >=3.8 ; extra == 'dev'
Requires-Dist: mypy >=0.800 ; extra == 'dev'
Requires-Dist: pytest-cov >=2.0 ; extra == 'dev'
Requires-Dist: pytest >=6.0 ; extra == 'dev'
Provides-Extra: full
Requires-Dist: aiofiles >=0.7 ; extra == 'full'
Requires-Dist: celery >=5.2 ; extra == 'full'
Requires-Dist: fastapi >=0.68 ; extra == 'full'
Requires-Dist: flask >=2.0 ; extra == 'full'
Requires-Dist: psycopg2-binary >=2.9 ; extra == 'full'
Requires-Dist: pymongo >=4.0 ; extra == 'full'
Requires-Dist: redis >=4.0 ; extra == 'full'
Requires-Dist: uvicorn >=0.15 ; extra == 'full'
Requires-Dist: websockets >=10.0 ; extra == 'full'
